pixel_sizes/__init__.py
pixel_sizes/_version.py
pixel_sizes/py.typed
pixel_sizes-0.2.2.dist-info/LICENSE
pixel_sizes-0.2.2.dist-info/METADATA
pixel_sizes-0.2.2.dist-info/WHEEL
pixel_sizes-0.2.2.dist-info/top_level.txt
pixel_sizes-0.2.2.dist-info/RECORD
