Metadata-Version: 2.2
Name: pixel_sizes
Version: 0.2.2
Summary: Pixel sizes
Author-email: Yui KITSU <kitsuyui+github@kitsuyui.com>
License: Copyright 2022-2025 Kitsu Yui
Project-URL: Homepage, https://github.com/kitsuyui/python-pixel-sizes
Classifier: License :: OSI Approved :: BSD License
Classifier: Programming Language :: Python :: 3.9
Classifier: Programming Language :: Python :: 3.10
Classifier: Programming Language :: Python :: 3.11
Classifier: Programming Language :: Python :: 3.12
Classifier: Programming Language :: Python :: 3.13
Classifier: Intended Audience :: Developers
Classifier: Topic :: Software Development :: Libraries
Requires-Python: >=3.9
License-File: LICENSE
